Battleship/Lab5/PISOSR10bit.v
module PISOSR10bit (bit_out, load, sr_clock, data, rst);
	input sr_clock, load, rst;
	input [7:0] data;
	output bit_out;
	
	reg [9:0] buffer = 10'b1111111111;
	
	assign bit_out = buffer[9];
	
	always @(posedge sr_clock or posedge rst)
		if (rst) buffer <= 10'b0;
		else if (load) buffer <= {1'b0, data, 1'b1};
		else buffer <= {buffer[8:0], 1'b1}; // shift out

endmodule

SourceCode/buffer.v
module buffer(buf_out, buf_in, buf_en);
	output buf_out;
	input buf_in, buf_en;
	
	assign buf_out = buf_en ? buf_in : 1'b1;
endmodule

SourceCode/bsc.v
module bsc (sr_clock, clk16x, bsc_en);
	input clk16x;
	input bsc_en;
	output sr_clock;    
	
	reg [3:0] bsc_count = 4'b0;
	
	assign sr_clock = ~bsc_count[3] & bsc_en;
	
	always@(posedge clk16x)
		if (bsc_en) bsc_count <= bsc_count + 1'b1;
		else bsc_count <= 4'b0;

endmodule

Battleship/Lab5/serial_out/bic.v
module bic (seq_complete, sr_clock, bic_en);
	input bic_en, sr_clock;
	output seq_complete;
	
	reg [3:0] bic_count = 4'b0;
	
	always@(posedge sr_clock)
		if (bic_en) bic_count <= bic_count + 1'b1;
		else bic_count <= 4'b0;
	
	assign seq_complete = bic_count[3] & ~bic_count[2] & bic_count[1] & bic_count[0];
endmodule

Battleship/Lab5/serial_out/serialOutTestbench.v
`include "bic.v"
`include "bsc.v"
`include "PISOSR10bit.v"
`include "buffer.v"

module sramTestBench;
	wire [7:0] data_in;
	wire transmit_en, load, character_sent, sr_clock, clk, buf_in, buf_out, rst;
	
	bic bic0 (character_sent, sr_clock, transmit_en);
	bsc bsc0 (sr_clock, clk, transmit_en);
	buffer buf0 (buf_out, buf_in, transmit_en);
	PISOSR10bit piso (buf_in, load, sr_clock, data_in, rst);
	
	Tester aTester (transmit_en, data_in, load, clk);
	
	initial
		begin 
			$dumpfile("serial_out.vcd");
			$dumpvars(4,bic0,bsc0,piso,buf0);
	end
endmodule



module Tester(transmit_en, data_in, load, clk);
	output reg [7:0] data_in;
	output reg transmit_en, load;
	output reg clk = 1'b1;

	
	parameter stimDelay = 20;
	
	initial begin
		forever
			#stimDelay clk <= ~clk;
	end
		
	initial
		begin
			data_in <= 8'b10011001; load <= 1'b1; transmit_en <= 1'b0;
			#(10 *stimDelay); transmit_en <= 1'b1;
			#stimDelay; load <= 1'b0;
			#(1000 * stimDelay);
			$finish;
		end 
endmodule

Battleship/Lab5/serial_out/serial_out.vcd
$date
	Wed Feb 17 22:12:02 2016
$end
$version
	Icarus Verilog
$end
$timescale
	1s
$end
$scope module sramTestBench $end
$scope module bic0 $end
$var wire 1 ! bic_en $end
$var wire 1 " seq_complete $end
$var wire 1 # sr_clock $end
$var reg 4 $ bic_count [3:0] $end
$upscope $end
$upscope $end
$scope module sramTestBench $end
$scope module bsc0 $end
$var wire 1 ! bsc_en $end
$var wire 1 % clk16x $end
$var wire 1 # sr_clock $end
$var reg 4 & bsc_count [3:0] $end
$upscope $end
$upscope $end
$scope module sramTestBench $end
$scope module piso $end
$var wire 8 ' data [7:0] $end
$var wire 1 ( load $end
$var wire 1 ) rst $end
$var wire 1 # sr_clock $end
$var wire 1 * bit_out $end
$var reg 10 + buffer [9:0] $end
$upscope $end
$upscope $end
$scope module sramTestBench $end
$scope module buf0 $end
$var wire 1 ! buf_en $end
$var wire 1 , buf_out $end
$var wire 1 * buf_in $end
$upscope $end
$upscope $end
$enddefinitions $end
#0
$dumpvars
1,
b1111111111 +
1*
z)
1(
b10011001 '
b0 &
1%
b0 $
0#
0"
0!
$end
#20
0%
#40
1%
#60
0%
#80
1%
#100
0%
#120
1%
#140
0%
#160
1%
#180
0%
#200
0,
0*
b1 $
b100110011 +
b1 &
1#
1%
1!
#220
0%
0(
#240
b10 &
1%
#260
0%
#280
b11 &
1%
#300
0%
#320
b100 &
1%
#340
0%
#360
b101 &
1%
#380
0%
#400
b110 &
1%
#420
0%
#440
b111 &
1%
#460
0%
#480
0#
b1000 &
1%
#500
0%
#520
b1001 &
1%
#540
0%
#560
b1010 &
1%
#580
0%
#600
b1011 &
1%
#620
0%
#640
b1100 &
1%
#660
0%
#680
b1101 &
1%
#700
0%
#720
b1110 &
1%
#740
0%
#760
b1111 &
1%
#780
0%
#800
1,
1*
b10 $
b1001100111 +
1#
b0 &
1%
#820
0%
#840
b1 &
1%
#860
0%
#880
b10 &
1%
#900
0%
#920
b11 &
1%
#940
0%
#960
b100 &
1%
#980
0%
#1000
b101 &
1%
#1020
0%
#1040
b110 &
1%
#1060
0%
#1080
b111 &
1%
#1100
0%
#1120
0#
b1000 &
1%
#1140
0%
#1160
b1001 &
1%
#1180
0%
#1200
b1010 &
1%
#1220
0%
#1240
b1011 &
1%
#1260
0%
#1280
b1100 &
1%
#1300
0%
#1320
b1101 &
1%
#1340
0%
#1360
b1110 &
1%
#1380
0%
#1400
b1111 &
1%
#1420
0%
#1440
0,
0*
b11 $
b11001111 +
1#
b0 &
1%
#1460
0%
#1480
b1 &
1%
#1500
0%
#1520
b10 &
1%
#1540
0%
#1560
b11 &
1%
#1580
0%
#1600
b100 &
1%
#1620
0%
#1640
b101 &
1%
#1660
0%
#1680
b110 &
1%
#1700
0%
#1720
b111 &
1%
#1740
0%
#1760
0#
b1000 &
1%
#1780
0%
#1800
b1001 &
1%
#1820
0%
#1840
b1010 &
1%
#1860
0%
#1880
b1011 &
1%
#1900
0%
#1920
b1100 &
1%
#1940
0%
#1960
b1101 &
1%
#1980
0%
#2000
b1110 &
1%
#2020
0%
#2040
b1111 &
1%
#2060
0%
#2080
b100 $
b110011111 +
1#
b0 &
1%
#2100
0%
#2120
b1 &
1%
#2140
0%
#2160
b10 &
1%
#2180
0%
#2200
b11 &
1%
#2220
0%
#2240
b100 &
1%
#2260
0%
#2280
b101 &
1%
#2300
0%
#2320
b110 &
1%
#2340
0%
#2360
b111 &
1%
#2380
0%
#2400
0#
b1000 &
1%
#2420
0%
#2440
b1001 &
1%
#2460
0%
#2480
b1010 &
1%
#2500
0%
#2520
b1011 &
1%
#2540
0%
#2560
b1100 &
1%
#2580
0%
#2600
b1101 &
1%
#2620
0%
#2640
b1110 &
1%
#2660
0%
#2680
b1111 &
1%
#2700
0%
#2720
1,
1*
b101 $
b1100111111 +
1#
b0 &
1%
#2740
0%
#2760
b1 &
1%
#2780
0%
#2800
b10 &
1%
#2820
0%
#2840
b11 &
1%
#2860
0%
#2880
b100 &
1%
#2900
0%
#2920
b101 &
1%
#2940
0%
#2960
b110 &
1%
#2980
0%
#3000
b111 &
1%
#3020
0%
#3040
0#
b1000 &
1%
#3060
0%
#3080
b1001 &
1%
#3100
0%
#3120
b1010 &
1%
#3140
0%
#3160
b1011 &
1%
#3180
0%
#3200
b1100 &
1%
#3220
0%
#3240
b1101 &
1%
#3260
0%
#3280
b1110 &
1%
#3300
0%
#3320
b1111 &
1%
#3340
0%
#3360
b110 $
b1001111111 +
1#
b0 &
1%
#3380
0%
#3400
b1 &
1%
#3420
0%
#3440
b10 &
1%
#3460
0%
#3480
b11 &
1%
#3500
0%
#3520
b100 &
1%
#3540
0%
#3560
b101 &
1%
#3580
0%
#3600
b110 &
1%
#3620
0%
#3640
b111 &
1%
#3660
0%
#3680
0#
b1000 &
1%
#3700
0%
#3720
b1001 &
1%
#3740
0%
#3760
b1010 &
1%
#3780
0%
#3800
b1011 &
1%
#3820
0%
#3840
b1100 &
1%
#3860
0%
#3880
b1101 &
1%
#3900
0%
#3920
b1110 &
1%
#3940
0%
#3960
b1111 &
1%
#3980
0%
#4000
0,
0*
b111 $
b11111111 +
1#
b0 &
1%
#4020
0%
#4040
b1 &
1%
#4060
0%
#4080
b10 &
1%
#4100
0%
#4120
b11 &
1%
#4140
0%
#4160
b100 &
1%
#4180
0%
#4200
b101 &
1%
#4220
0%
#4240
b110 &
1%
#4260
0%
#4280
b111 &
1%
#4300
0%
#4320
0#
b1000 &
1%
#4340
0%
#4360
b1001 &
1%
#4380
0%
#4400
b1010 &
1%
#4420
0%
#4440
b1011 &
1%
#4460
0%
#4480
b1100 &
1%
#4500
0%
#4520
b1101 &
1%
#4540
0%
#4560
b1110 &
1%
#4580
0%
#4600
b1111 &
1%
#4620
0%
#4640
b1000 $
b111111111 +
1#
b0 &
1%
#4660
0%
#4680
b1 &
1%
#4700
0%
#4720
b10 &
1%
#4740
0%
#4760
b11 &
1%
#4780
0%
#4800
b100 &
1%
#4820
0%
#4840
b101 &
1%
#4860
0%
#4880
b110 &
1%
#4900
0%
#4920
b111 &
1%
#4940
0%
#4960
0#
b1000 &
1%
#4980
0%
#5000
b1001 &
1%
#5020
0%
#5040
b1010 &
1%
#5060
0%
#5080
b1011 &
1%
#5100
0%
#5120
b1100 &
1%
#5140
0%
#5160
b1101 &
1%
#5180
0%
#5200
b1110 &
1%
#5220
0%
#5240
b1111 &
1%
#5260
0%
#5280
1,
1*
b1001 $
b1111111111 +
1#
b0 &
1%
#5300
0%
#5320
b1 &
1%
#5340
0%
#5360
b10 &
1%
#5380
0%
#5400
b11 &
1%
#5420
0%
#5440
b100 &
1%
#5460
0%
#5480
b101 &
1%
#5500
0%
#5520
b110 &
1%
#5540
0%
#5560
b111 &
1%
#5580
0%
#5600
0#
b1000 &
1%
#5620
0%
#5640
b1001 &
1%
#5660
0%
#5680
b1010 &
1%
#5700
0%
#5720
b1011 &
1%
#5740
0%
#5760
b1100 &
1%
#5780
0%
#5800
b1101 &
1%
#5820
0%
#5840
b1110 &
1%
#5860
0%
#5880
b1111 &
1%
#5900
0%
#5920
b1010 $
1#
b0 &
1%
#5940
0%
#5960
b1 &
1%
#5980
0%
#6000
b10 &
1%
#6020
0%
#6040
b11 &
1%
#6060
0%
#6080
b100 &
1%
#6100
0%
#6120
b101 &
1%
#6140
0%
#6160
b110 &
1%
#6180
0%
#6200
b111 &
1%
#6220
0%
#6240
0#
b1000 &
1%
#6260
0%
#6280
b1001 &
1%
#6300
0%
#6320
b1010 &
1%
#6340
0%
#6360
b1011 &
1%
#6380
0%
#6400
b1100 &
1%
#6420
0%
#6440
b1101 &
1%
#6460
0%
#6480
b1110 &
1%
#6500
0%
#6520
b1111 &
1%
#6540
0%
#6560
1"
b1011 $
1#
b0 &
1%
#6580
0%
#6600
b1 &
1%
#6620
0%
#6640
b10 &
1%
#6660
0%
#6680
b11 &
1%
#6700
0%
#6720
b100 &
1%
#6740
0%
#6760
b101 &
1%
#6780
0%
#6800
b110 &
1%
#6820
0%
#6840
b111 &
1%
#6860
0%
#6880
0#
b1000 &
1%
#6900
0%
#6920
b1001 &
1%
#6940
0%
#6960
b1010 &
1%
#6980
0%
#7000
b1011 &
1%
#7020
0%
#7040
b1100 &
1%
#7060
0%
#7080
b1101 &
1%
#7100
0%
#7120
b1110 &
1%
#7140
0%
#7160
b1111 &
1%
#7180
0%
#7200
0"
b1100 $
1#
b0 &
1%
#7220
0%
#7240
b1 &
1%
#7260
0%
#7280
b10 &
1%
#7300
0%
#7320
b11 &
1%
#7340
0%
#7360
b100 &
1%
#7380
0%
#7400
b101 &
1%
#7420
0%
#7440
b110 &
1%
#7460
0%
#7480
b111 &
1%
#7500
0%
#7520
0#
b1000 &
1%
#7540
0%
#7560
b1001 &
1%
#7580
0%
#7600
b1010 &
1%
#7620
0%
#7640
b1011 &
1%
#7660
0%
#7680
b1100 &
1%
#7700
0%
#7720
b1101 &
1%
#7740
0%
#7760
b1110 &
1%
#7780
0%
#7800
b1111 &
1%
#7820
0%
#7840
b1101 $
1#
b0 &
1%
#7860
0%
#7880
b1 &
1%
#7900
0%
#7920
b10 &
1%
#7940
0%
#7960
b11 &
1%
#7980
0%
#8000
b100 &
1%
#8020
0%
#8040
b101 &
1%
#8060
0%
#8080
b110 &
1%
#8100
0%
#8120
b111 &
1%
#8140
0%
#8160
0#
b1000 &
1%
#8180
0%
#8200
b1001 &
1%
#8220
0%
#8240
b1010 &
1%
#8260
0%
#8280
b1011 &
1%
#8300
0%
#8320
b1100 &
1%
#8340
0%
#8360
b1101 &
1%
#8380
0%
#8400
b1110 &
1%
#8420
0%
#8440
b1111 &
1%
#8460
0%
#8480
b1110 $
1#
b0 &
1%
#8500
0%
#8520
b1 &
1%
#8540
0%
#8560
b10 &
1%
#8580
0%
#8600
b11 &
1%
#8620
0%
#8640
b100 &
1%
#8660
0%
#8680
b101 &
1%
#8700
0%
#8720
b110 &
1%
#8740
0%
#8760
b111 &
1%
#8780
0%
#8800
0#
b1000 &
1%
#8820
0%
#8840
b1001 &
1%
#8860
0%
#8880
b1010 &
1%
#8900
0%
#8920
b1011 &
1%
#8940
0%
#8960
b1100 &
1%
#8980
0%
#9000
b1101 &
1%
#9020
0%
#9040
b1110 &
1%
#9060
0%
#9080
b1111 &
1%
#9100
0%
#9120
b1111 $
1#
b0 &
1%
#9140
0%
#9160
b1 &
1%
#9180
0%
#9200
b10 &
1%
#9220
0%
#9240
b11 &
1%
#9260
0%
#9280
b100 &
1%
#9300
0%
#9320
b101 &
1%
#9340
0%
#9360
b110 &
1%
#9380
0%
#9400
b111 &
1%
#9420
0%
#9440
0#
b1000 &
1%
#9460
0%
#9480
b1001 &
1%
#9500
0%
#9520
b1010 &
1%
#9540
0%
#9560
b1011 &
1%
#9580
0%
#9600
b1100 &
1%
#9620
0%
#9640
b1101 &
1%
#9660
0%
#9680
b1110 &
1%
#9700
0%
#9720
b1111 &
1%
#9740
0%
#9760
b0 $
1#
b0 &
1%
#9780
0%
#9800
b1 &
1%
#9820
0%
#9840
b10 &
1%
#9860
0%
#9880
b11 &
1%
#9900
0%
#9920
b100 &
1%
#9940
0%
#9960
b101 &
1%
#9980
0%
#10000
b110 &
1%
#10020
0%
#10040
b111 &
1%
#10060
0%
#10080
0#
b1000 &
1%
#10100
0%
#10120
b1001 &
1%
#10140
0%
#10160
b1010 &
1%
#10180
0%
#10200
b1011 &
1%
#10220
0%
#10240
b1100 &
1%
#10260
0%
#10280
b1101 &
1%
#10300
0%
#10320
b1110 &
1%
#10340
0%
#10360
b1111 &
1%
#10380
0%
#10400
b1 $
1#
b0 &
1%
#10420
0%
#10440
b1 &
1%
#10460
0%
#10480
b10 &
1%
#10500
0%
#10520
b11 &
1%
#10540
0%
#10560
b100 &
1%
#10580
0%
#10600
b101 &
1%
#10620
0%
#10640
b110 &
1%
#10660
0%
#10680
b111 &
1%
#10700
0%
#10720
0#
b1000 &
1%
#10740
0%
#10760
b1001 &
1%
#10780
0%
#10800
b1010 &
1%
#10820
0%
#10840
b1011 &
1%
#10860
0%
#10880
b1100 &
1%
#10900
0%
#10920
b1101 &
1%
#10940
0%
#10960
b1110 &
1%
#10980
0%
#11000
b1111 &
1%
#11020
0%
#11040
b10 $
1#
b0 &
1%
#11060
0%
#11080
b1 &
1%
#11100
0%
#11120
b10 &
1%
#11140
0%
#11160
b11 &
1%
#11180
0%
#11200
b100 &
1%
#11220
0%
#11240
b101 &
1%
#11260
0%
#11280
b110 &
1%
#11300
0%
#11320
b111 &
1%
#11340
0%
#11360
0#
b1000 &
1%
#11380
0%
#11400
b1001 &
1%
#11420
0%
#11440
b1010 &
1%
#11460
0%
#11480
b1011 &
1%
#11500
0%
#11520
b1100 &
1%
#11540
0%
#11560
b1101 &
1%
#11580
0%
#11600
b1110 &
1%
#11620
0%
#11640
b1111 &
1%
#11660
0%
#11680
b11 $
1#
b0 &
1%
#11700
0%
#11720
b1 &
1%
#11740
0%
#11760
b10 &
1%
#11780
0%
#11800
b11 &
1%
#11820
0%
#11840
b100 &
1%
#11860
0%
#11880
b101 &
1%
#11900
0%
#11920
b110 &
1%
#11940
0%
#11960
b111 &
1%
#11980
0%
#12000
0#
b1000 &
1%
#12020
0%
#12040
b1001 &
1%
#12060
0%
#12080
b1010 &
1%
#12100
0%
#12120
b1011 &
1%
#12140
0%
#12160
b1100 &
1%
#12180
0%
#12200
b1101 &
1%
#12220
0%
#12240
b1110 &
1%
#12260
0%
#12280
b1111 &
1%
#12300
0%
#12320
b100 $
1#
b0 &
1%
#12340
0%
#12360
b1 &
1%
#12380
0%
#12400
b10 &
1%
#12420
0%
#12440
b11 &
1%
#12460
0%
#12480
b100 &
1%
#12500
0%
#12520
b101 &
1%
#12540
0%
#12560
b110 &
1%
#12580
0%
#12600
b111 &
1%
#12620
0%
#12640
0#
b1000 &
1%
#12660
0%
#12680
b1001 &
1%
#12700
0%
#12720
b1010 &
1%
#12740
0%
#12760
b1011 &
1%
#12780
0%
#12800
b1100 &
1%
#12820
0%
#12840
b1101 &
1%
#12860
0%
#12880
b1110 &
1%
#12900
0%
#12920
b1111 &
1%
#12940
0%
#12960
b101 $
1#
b0 &
1%
#12980
0%
#13000
b1 &
1%
#13020
0%
#13040
b10 &
1%
#13060
0%
#13080
b11 &
1%
#13100
0%
#13120
b100 &
1%
#13140
0%
#13160
b101 &
1%
#13180
0%
#13200
b110 &
1%
#13220
0%
#13240
b111 &
1%
#13260
0%
#13280
0#
b1000 &
1%
#13300
0%
#13320
b1001 &
1%
#13340
0%
#13360
b1010 &
1%
#13380
0%
#13400
b1011 &
1%
#13420
0%
#13440
b1100 &
1%
#13460
0%
#13480
b1101 &
1%
#13500
0%
#13520
b1110 &
1%
#13540
0%
#13560
b1111 &
1%
#13580
0%
#13600
b110 $
1#
b0 &
1%
#13620
0%
#13640
b1 &
1%
#13660
0%
#13680
b10 &
1%
#13700
0%
#13720
b11 &
1%
#13740
0%
#13760
b100 &
1%
#13780
0%
#13800
b101 &
1%
#13820
0%
#13840
b110 &
1%
#13860
0%
#13880
b111 &
1%
#13900
0%
#13920
0#
b1000 &
1%
#13940
0%
#13960
b1001 &
1%
#13980
0%
#14000
b1010 &
1%
#14020
0%
#14040
b1011 &
1%
#14060
0%
#14080
b1100 &
1%
#14100
0%
#14120
b1101 &
1%
#14140
0%
#14160
b1110 &
1%
#14180
0%
#14200
b1111 &
1%
#14220
0%
#14240
b111 $
1#
b0 &
1%
#14260
0%
#14280
b1 &
1%
#14300
0%
#14320
b10 &
1%
#14340
0%
#14360
b11 &
1%
#14380
0%
#14400
b100 &
1%
#14420
0%
#14440
b101 &
1%
#14460
0%
#14480
b110 &
1%
#14500
0%
#14520
b111 &
1%
#14540
0%
#14560
0#
b1000 &
1%
#14580
0%
#14600
b1001 &
1%
#14620
0%
#14640
b1010 &
1%
#14660
0%
#14680
b1011 &
1%
#14700
0%
#14720
b1100 &
1%
#14740
0%
#14760
b1101 &
1%
#14780
0%
#14800
b1110 &
1%
#14820
0%
#14840
b1111 &
1%
#14860
0%
#14880
b1000 $
1#
b0 &
1%
#14900
0%
#14920
b1 &
1%
#14940
0%
#14960
b10 &
1%
#14980
0%
#15000
b11 &
1%
#15020
0%
#15040
b100 &
1%
#15060
0%
#15080
b101 &
1%
#15100
0%
#15120
b110 &
1%
#15140
0%
#15160
b111 &
1%
#15180
0%
#15200
0#
b1000 &
1%
#15220
0%
#15240
b1001 &
1%
#15260
0%
#15280
b1010 &
1%
#15300
0%
#15320
b1011 &
1%
#15340
0%
#15360
b1100 &
1%
#15380
0%
#15400
b1101 &
1%
#15420
0%
#15440
b1110 &
1%
#15460
0%
#15480
b1111 &
1%
#15500
0%
#15520
b1001 $
1#
b0 &
1%
#15540
0%
#15560
b1 &
1%
#15580
0%
#15600
b10 &
1%
#15620
0%
#15640
b11 &
1%
#15660
0%
#15680
b100 &
1%
#15700
0%
#15720
b101 &
1%
#15740
0%
#15760
b110 &
1%
#15780
0%
#15800
b111 &
1%
#15820
0%
#15840
0#
b1000 &
1%
#15860
0%
#15880
b1001 &
1%
#15900
0%
#15920
b1010 &
1%
#15940
0%
#15960
b1011 &
1%
#15980
0%
#16000
b1100 &
1%
#16020
0%
#16040
b1101 &
1%
#16060
0%
#16080
b1110 &
1%
#16100
0%
#16120
b1111 &
1%
#16140
0%
#16160
b1010 $
1#
b0 &
1%
#16180
0%
#16200
b1 &
1%
#16220
0%
#16240
b10 &
1%
#16260
0%
#16280
b11 &
1%
#16300
0%
#16320
b100 &
1%
#16340
0%
#16360
b101 &
1%
#16380
0%
#16400
b110 &
1%
#16420
0%
#16440
b111 &
1%
#16460
0%
#16480
0#
b1000 &
1%
#16500
0%
#16520
b1001 &
1%
#16540
0%
#16560
b1010 &
1%
#16580
0%
#16600
b1011 &
1%
#16620
0%
#16640
b1100 &
1%
#16660
0%
#16680
b1101 &
1%
#16700
0%
#16720
b1110 &
1%
#16740
0%
#16760
b1111 &
1%
#16780
0%
#16800
1"
b1011 $
1#
b0 &
1%
#16820
0%
#16840
b1 &
1%
#16860
0%
#16880
b10 &
1%
#16900
0%
#16920
b11 &
1%
#16940
0%
#16960
b100 &
1%
#16980
0%
#17000
b101 &
1%
#17020
0%
#17040
b110 &
1%
#17060
0%
#17080
b111 &
1%
#17100
0%
#17120
0#
b1000 &
1%
#17140
0%
#17160
b1001 &
1%
#17180
0%
#17200
b1010 &
1%
#17220
0%
#17240
b1011 &
1%
#17260
0%
#17280
b1100 &
1%
#17300
0%
#17320
b1101 &
1%
#17340
0%
#17360
b1110 &
1%
#17380
0%
#17400
b1111 &
1%
#17420
0%
#17440
0"
b1100 $
1#
b0 &
1%
#17460
0%
#17480
b1 &
1%
#17500
0%
#17520
b10 &
1%
#17540
0%
#17560
b11 &
1%
#17580
0%
#17600
b100 &
1%
#17620
0%
#17640
b101 &
1%
#17660
0%
#17680
b110 &
1%
#17700
0%
#17720
b111 &
1%
#17740
0%
#17760
0#
b1000 &
1%
#17780
0%
#17800
b1001 &
1%
#17820
0%
#17840
b1010 &
1%
#17860
0%
#17880
b1011 &
1%
#17900
0%
#17920
b1100 &
1%
#17940
0%
#17960
b1101 &
1%
#17980
0%
#18000
b1110 &
1%
#18020
0%
#18040
b1111 &
1%
#18060
0%
#18080
b1101 $
1#
b0 &
1%
#18100
0%
#18120
b1 &
1%
#18140
0%
#18160
b10 &
1%
#18180
0%
#18200
b11 &
1%
#18220
0%
#18240
b100 &
1%
#18260
0%
#18280
b101 &
1%
#18300
0%
#18320
b110 &
1%
#18340
0%
#18360
b111 &
1%
#18380
0%
#18400
0#
b1000 &
1%
#18420
0%
#18440
b1001 &
1%
#18460
0%
#18480
b1010 &
1%
#18500
0%
#18520
b1011 &
1%
#18540
0%
#18560
b1100 &
1%
#18580
0%
#18600
b1101 &
1%
#18620
0%
#18640
b1110 &
1%
#18660
0%
#18680
b1111 &
1%
#18700
0%
#18720
b1110 $
1#
b0 &
1%
#18740
0%
#18760
b1 &
1%
#18780
0%
#18800
b10 &
1%
#18820
0%
#18840
b11 &
1%
#18860
0%
#18880
b100 &
1%
#18900
0%
#18920
b101 &
1%
#18940
0%
#18960
b110 &
1%
#18980
0%
#19000
b111 &
1%
#19020
0%
#19040
0#
b1000 &
1%
#19060
0%
#19080
b1001 &
1%
#19100
0%
#19120
b1010 &
1%
#19140
0%
#19160
b1011 &
1%
#19180
0%
#19200
b1100 &
1%
#19220
0%
#19240
b1101 &
1%
#19260
0%
#19280
b1110 &
1%
#19300
0%
#19320
b1111 &
1%
#19340
0%
#19360
b1111 $
1#
b0 &
1%
#19380
0%
#19400
b1 &
1%
#19420
0%
#19440
b10 &
1%
#19460
0%
#19480
b11 &
1%
#19500
0%
#19520
b100 &
1%
#19540
0%
#19560
b101 &
1%
#19580
0%
#19600
b110 &
1%
#19620
0%
#19640
b111 &
1%
#19660
0%
#19680
0#
b1000 &
1%
#19700
0%
#19720
b1001 &
1%
#19740
0%
#19760
b1010 &
1%
#19780
0%
#19800
b1011 &
1%
#19820
0%
#19840
b1100 &
1%
#19860
0%
#19880
b1101 &
1%
#19900
0%
#19920
b1110 &
1%
#19940
0%
#19960
b1111 &
1%
#19980
0%
#20000
b0 $
1#
b0 &
1%
#20020
0%
#20040
b1 &
1%
#20060
0%
#20080
b10 &
1%
#20100
0%
#20120
b11 &
1%
#20140
0%
#20160
b100 &
1%
#20180
0%
#20200
b101 &
1%
