Battleship/Lab5/serial_out/SIPOSR10bit.v
module SIPOSR10bit (dataout, datain, sr_clock, rst);
	output [7:0] dataout;
	input datain, sr_clock, rst;
	
	reg [9:0] buffer = 10'b0;
	
	assign dataout = buffer[8:1];
	
	always @(posedge sr_clock or posedge rst)
		if (rst) buffer <= 10'b0;
		else buffer <= {datain, buffer[9:1]};
endmodule

SourceCode/bsc.v
module bsc (sr_clock, clk16x, bsc_en);
	input clk16x;
	input bsc_en;
	output sr_clock;    
	
	reg [3:0] bsc_count = 4'b0;
	
	assign sr_clock = ~bsc_count[3] & bsc_en;
	
	always@(posedge clk16x)
		if (bsc_en) bsc_count <= bsc_count + 1'b1;
		else bsc_count <= 4'b0;

endmodule

Battleship/Lab5/serial_in/bic.v
module bic (seq_complete, sr_clock, bic_en);
	input bic_en, sr_clock;
	output seq_complete;
	
	reg [3:0] bic_count = 4'b0;
	
	always@(posedge sr_clock)
		if (bic_en) bic_count <= bic_count + 1'b1;
		else bic_count <= 4'b0;
	
	assign seq_complete = bic_count[3] & ~bic_count[2] & bic_count[1] & ~bic_count[0];
endmodule

Battleship/Lab5/serial_out/startBitDetect.v
module startBitDetect(recv_en, data_in, char_received);
	output reg recv_en = 1'b0;
	input data_in, char_received;

	always @(negedge data_in or posedge char_received)
		if (char_received) recv_en <= 1'b0;
		else recv_en <= 1'b1;
endmodule

Battleship/Lab5/serial_in/serial_in_testbench.v
`include "bic.v"
`include "bsc.v"
`include "SIPOSR10bit.v"
`include "startBitDetect.v"

module serial_in_testbench;
	wire [7:0] data_in;
	wire serial_in, receive_en, sr_clock, char_received, clk;
	
	startBitDetect sbd (receive_en, serial_in, char_received);
	bic bic0 (char_received, ~sr_clock, receive_en);
	bsc bsc0 (sr_clock, clk, receive_en);
	SIPOSR10bit sipo (data_in, serial_in, ~sr_clock, rst);
	
	Tester aTester (serial_in, clk);
	
	initial
		begin 
			$dumpfile("serial_in.vcd");
			$dumpvars(4,bic0,bsc0,sipo,sbd);
	end
endmodule



module Tester(serial_in, clk);
	output reg serial_in = 1'b1;
	output reg clk = 1'b1;

	
	parameter stimDelay = 20;
	
	initial begin
		forever
			#stimDelay clk <= ~clk;
	end
		
	initial
		begin
			#(20 * stimDelay); serial_in <= 1'b0;
			#(32 * stimDelay); serial_in <= 1'b1;
			#(32 * stimDelay); serial_in <= 1'b0;
			#(32 * stimDelay); serial_in <= 1'b0;
			#(32 * stimDelay); serial_in <= 1'b1;
			#(32 * stimDelay); serial_in <= 1'b1;
			#(32 * stimDelay); serial_in <= 1'b0;
			#(32 * stimDelay); serial_in <= 1'b0;
			#(32 * stimDelay); serial_in <= 1'b1;
			#(32 * stimDelay); serial_in <= 1'b1;
			#(100 * stimDelay);
			$finish;
		end 
endmodule

Battleship/Lab5/serial_in/serial_in.vcd
$date
	Wed Feb 17 23:29:36 2016
$end
$version
	Icarus Verilog
$end
$timescale
	1s
$end
$scope module serial_in_testbench $end
$scope module bic0 $end
$var wire 1 ! seq_complete $end
$var wire 1 " sr_clock $end
$var wire 1 # bic_en $end
$var reg 4 $ bic_count [3:0] $end
$upscope $end
$upscope $end
$scope module serial_in_testbench $end
$scope module bsc0 $end
$var wire 1 % clk16x $end
$var wire 1 & sr_clock $end
$var wire 1 # bsc_en $end
$var reg 4 ' bsc_count [3:0] $end
$upscope $end
$upscope $end
$scope module serial_in_testbench $end
$scope module sipo $end
$var wire 1 ( datain $end
$var wire 1 ) rst $end
$var wire 1 * sr_clock $end
$var wire 8 + dataout [7:0] $end
$var reg 10 , buffer [9:0] $end
$upscope $end
$upscope $end
$scope module serial_in_testbench $end
$scope module sbd $end
$var wire 1 ! char_received $end
$var wire 1 ( data_in $end
$var reg 1 # recv_en $end
$upscope $end
$upscope $end
$enddefinitions $end
#0
$dumpvars
b1000000000 ,
b0 +
1*
z)
1(
b0 '
0&
1%
b0 $
0#
1"
0!
$end
#20
0%
#40
1%
#60
0%
#80
1%
#100
0%
#120
1%
#140
0%
#160
1%
#180
0%
#200
1%
#220
0%
#240
1%
#260
0%
#280
1%
#300
0%
#320
1%
#340
0%
#360
1%
#380
0%
#400
0*
0"
1&
1#
1%
0(
#420
0%
#440
b1 '
1%
#460
0%
#480
b10 '
1%
#500
0%
#520
b11 '
1%
#540
0%
#560
b100 '
1%
#580
0%
#600
b101 '
1%
#620
0%
#640
b110 '
1%
#660
0%
#680
b111 '
1%
#700
0%
#720
b10000000 +
b100000000 ,
b1 $
1*
1"
0&
b1000 '
1%
#740
0%
#760
b1001 '
1%
#780
0%
#800
b1010 '
1%
#820
0%
#840
b1011 '
1%
#860
0%
#880
b1100 '
1%
#900
0%
#920
b1101 '
1%
#940
0%
#960
b1110 '
1%
#980
0%
#1000
b1111 '
1%
#1020
0%
#1040
0*
0"
1&
b0 '
1%
1(
#1060
0%
#1080
b1 '
1%
#1100
0%
#1120
b10 '
1%
#1140
0%
#1160
b11 '
1%
#1180
0%
#1200
b100 '
1%
#1220
0%
#1240
b101 '
1%
#1260
0%
#1280
b110 '
1%
#1300
0%
#1320
b111 '
1%
#1340
0%
#1360
b1000000 +
b1010000000 ,
b10 $
1*
1"
0&
b1000 '
1%
#1380
0%
#1400
b1001 '
1%
#1420
0%
#1440
b1010 '
1%
#1460
0%
#1480
b1011 '
1%
#1500
0%
#1520
b1100 '
1%
#1540
0%
#1560
b1101 '
1%
#1580
0%
#1600
b1110 '
1%
#1620
0%
#1640
b1111 '
1%
#1660
0%
#1680
0*
0"
1&
b0 '
1%
0(
#1700
0%
#1720
b1 '
1%
#1740
0%
#1760
b10 '
1%
#1780
0%
#1800
b11 '
1%
#1820
0%
#1840
b100 '
1%
#1860
0%
#1880
b101 '
1%
#1900
0%
#1920
b110 '
1%
#1940
0%
#1960
b111 '
1%
#1980
0%
#2000
b10100000 +
b101000000 ,
b11 $
1*
1"
0&
b1000 '
1%
#2020
0%
#2040
b1001 '
1%
#2060
0%
#2080
b1010 '
1%
#2100
0%
#2120
b1011 '
1%
#2140
0%
#2160
b1100 '
1%
#2180
0%
#2200
b1101 '
1%
#2220
0%
#2240
b1110 '
1%
#2260
0%
#2280
b1111 '
1%
#2300
0%
#2320
0*
0"
1&
b0 '
1%
#2340
0%
#2360
b1 '
1%
#2380
0%
#2400
b10 '
1%
#2420
0%
#2440
b11 '
1%
#2460
0%
#2480
b100 '
1%
#2500
0%
#2520
b101 '
1%
#2540
0%
#2560
b110 '
1%
#2580
0%
#2600
b111 '
1%
#2620
0%
#2640
b1010000 +
b10100000 ,
b100 $
1*
1"
0&
b1000 '
1%
#2660
0%
#2680
b1001 '
1%
#2700
0%
#2720
b1010 '
1%
#2740
0%
#2760
b1011 '
1%
#2780
0%
#2800
b1100 '
1%
#2820
0%
#2840
b1101 '
1%
#2860
0%
#2880
b1110 '
1%
#2900
0%
#2920
b1111 '
1%
#2940
0%
#2960
0*
0"
1&
b0 '
1%
1(
#2980
0%
#3000
b1 '
1%
#3020
0%
#3040
b10 '
1%
#3060
0%
#3080
b11 '
1%
#3100
0%
#3120
b100 '
1%
#3140
0%
#3160
b101 '
1%
#3180
0%
#3200
b110 '
1%
#3220
0%
#3240
b111 '
1%
#3260
0%
#3280
b101000 +
b1001010000 ,
b101 $
1*
1"
0&
b1000 '
1%
#3300
0%
#3320
b1001 '
1%
#3340
0%
#3360
b1010 '
1%
#3380
0%
#3400
b1011 '
1%
#3420
0%
#3440
b1100 '
1%
#3460
0%
#3480
b1101 '
1%
#3500
0%
#3520
b1110 '
1%
#3540
0%
#3560
b1111 '
1%
#3580
0%
#3600
0*
0"
1&
b0 '
1%
#3620
0%
#3640
b1 '
1%
#3660
0%
#3680
b10 '
1%
#3700
0%
#3720
b11 '
1%
#3740
0%
#3760
b100 '
1%
#3780
0%
#3800
b101 '
1%
#3820
0%
#3840
b110 '
1%
#3860
0%
#3880
b111 '
1%
#3900
0%
#3920
b10010100 +
b1100101000 ,
b110 $
1*
1"
0&
b1000 '
1%
#3940
0%
#3960
b1001 '
1%
#3980
0%
#4000
b1010 '
1%
#4020
0%
#4040
b1011 '
1%
#4060
0%
#4080
b1100 '
1%
#4100
0%
#4120
b1101 '
1%
#4140
0%
#4160
b1110 '
1%
#4180
0%
#4200
b1111 '
1%
#4220
0%
#4240
0*
0"
1&
b0 '
1%
0(
#4260
0%
#4280
b1 '
1%
#4300
0%
#4320
b10 '
1%
#4340
0%
#4360
b11 '
1%
#4380
0%
#4400
b100 '
1%
#4420
0%
#4440
b101 '
1%
#4460
0%
#4480
b110 '
1%
#4500
0%
#4520
b111 '
1%
#4540
0%
#4560
b11001010 +
b110010100 ,
b111 $
1*
1"
0&
b1000 '
1%
#4580
0%
#4600
b1001 '
1%
#4620
0%
#4640
b1010 '
1%
#4660
0%
#4680
b1011 '
1%
#4700
0%
#4720
b1100 '
1%
#4740
0%
#4760
b1101 '
1%
#4780
0%
#4800
b1110 '
1%
#4820
0%
#4840
b1111 '
1%
#4860
0%
#4880
0*
0"
1&
b0 '
1%
#4900
0%
#4920
b1 '
1%
#4940
0%
#4960
b10 '
1%
#4980
0%
#5000
b11 '
1%
#5020
0%
#5040
b100 '
1%
#5060
0%
#5080
b101 '
1%
#5100
0%
#5120
b110 '
1%
#5140
0%
#5160
b111 '
1%
#5180
0%
#5200
b1100101 +
b11001010 ,
b1000 $
1*
1"
0&
b1000 '
1%
#5220
0%
#5240
b1001 '
1%
#5260
0%
#5280
b1010 '
1%
#5300
0%
#5320
b1011 '
1%
#5340
0%
#5360
b1100 '
1%
#5380
0%
#5400
b1101 '
1%
#5420
0%
#5440
b1110 '
1%
#5460
0%
#5480
b1111 '
1%
#5500
0%
#5520
0*
0"
1&
b0 '
1%
1(
#5540
0%
#5560
b1 '
1%
#5580
0%
#5600
b10 '
1%
#5620
0%
#5640
b11 '
1%
#5660
0%
#5680
b100 '
1%
#5700
0%
#5720
b101 '
1%
#5740
0%
#5760
b110 '
1%
#5780
0%
#5800
b111 '
1%
#5820
0%
#5840
b110010 +
b1001100101 ,
b1001 $
1*
1"
0&
b1000 '
1%
#5860
0%
#5880
b1001 '
1%
#5900
0%
#5920
b1010 '
1%
#5940
0%
#5960
b1011 '
1%
#5980
0%
#6000
b1100 '
1%
#6020
0%
#6040
b1101 '
1%
#6060
0%
#6080
b1110 '
1%
#6100
0%
#6120
b1111 '
1%
#6140
0%
#6160
0*
0"
1&
b0 '
1%
#6180
0%
#6200
b1 '
1%
#6220
0%
#6240
b10 '
1%
#6260
0%
#6280
b11 '
1%
#6300
0%
#6320
b100 '
1%
#6340
0%
#6360
b101 '
1%
#6380
0%
#6400
b110 '
1%
#6420
0%
#6440
b111 '
1%
#6460
0%
#6480
0#
1!
b10011001 +
b1100110010 ,
b1010 $
1*
1"
0&
b1000 '
1%
#6500
0%
#6520
b0 '
1%
